<?xml version="1.0" encoding="utf-8"?>
<clothing-items>
 <clothing>
  <id>
   298460284
  </id>
  <name>
   Nike Umbrellas X-1980
  </name>
  <category>
   Umbrellas
  </category>
  <size>
   S
  </size>
  <color>
   Зеленый
  </color>
  <material>
   Нейлон
  </material>
  <price>
   197458
  </price>
  <rating>
   2.18
  </rating>
  <reviews>
   458920
  </reviews>
  <exclusive>
   yes
  </exclusive>
 </clothing>
 <clothing>
  <id>
   764811160
  </id>
  <name>
   Vans Shirt Q-3534
  </name>
  <category>
   Shirt
  </category>
  <size>
   XXL
  </size>
  <color>
   Голубой
  </color>
  <material>
   Кожа
  </material>
  <price>
   179254
  </price>
  <rating>
   1.01
  </rating>
  <reviews>
   229640
  </reviews>
 </clothing>
 <clothing>
  <id>
   210870334
  </id>
  <name>
   Fila Jeans R-9123
  </name>
  <category>
   Jeans
  </category>
  <size>
   S
  </size>
  <color>
   Оранжевый
  </color>
  <material>
   Шелк
  </material>
  <price>
   359176
  </price>
  <rating>
   3.7
  </rating>
  <reviews>
   642668
  </reviews>
  <exclusive>
   no
  </exclusive>
 </clothing>
 <clothing>
  <id>
   275062026
  </id>
  <name>
   Fila Skirt T-8901
  </name>
  <category>
   Skirt
  </category>
  <size>
   XXL
  </size>
  <color>
   Оранжевый
  </color>
  <material>
   Вискоза
  </material>
  <price>
   966451
  </price>
  <rating>
   2.82
  </rating>
  <reviews>
   405730
  </reviews>
  <new>
   -
  </new>
  <exclusive>
   yes
  </exclusive>
 </clothing>
 <clothing>
  <id>
   581927384
  </id>
  <name>
   Nike T-shirt J-5102
  </name>
  <category>
   T-shirt
  </category>
  <size>
   XL
  </size>
  <color>
   Оранжевый
  </color>
  <material>
   Хлопок
  </material>
  <price>
   353388
  </price>
  <rating>
   1.38
  </rating>
  <reviews>
   639398
  </reviews>
  <exclusive>
   no
  </exclusive>
  <sporty>
   no
  </sporty>
 </clothing>
 <clothing>
  <id>
   417358757
  </id>
  <name>
   Adidas Gloves G-7506
  </name>
  <category>
   Gloves
  </category>
  <size>
   M
  </size>
  <color>
   Красный
  </color>
  <material>
   Шерсть
  </material>
  <price>
   255906
  </price>
  <rating>
   4.41
  </rating>
  <reviews>
   638412
  </reviews>
  <new>
   -
  </new>
  <exclusive>
   yes
  </exclusive>
  <sporty>
   no
  </sporty>
 </clothing>
 <clothing>
  <id>
   691461212
  </id>
  <name>
   Addidas Pants O-4387
  </name>
  <category>
   Pants
  </category>
  <size>
   XXL
  </size>
  <color>
   Фиолетовый
  </color>
  <material>
   Вискоза
  </material>
  <price>
   370761
  </price>
  <rating>
   3.25
  </rating>
  <reviews>
   620919
  </reviews>
  <new>
   -
  </new>
  <exclusive>
   no
  </exclusive>
 </clothing>
 <clothing>
  <id>
   728995821
  </id>
  <name>
   Puma Jeans H-4552
  </name>
  <category>
   Jeans
  </category>
  <size>
   XXL
  </size>
  <color>
   Зеленый
  </color>
  <material>
   Хлопок
  </material>
  <price>
   630593
  </price>
  <rating>
   1.66
  </rating>
  <reviews>
   414891
  </reviews>
  <new>
   -
  </new>
  <exclusive>
   no
  </exclusive>
  <sporty>
   no
  </sporty>
 </clothing>
 <clothing>
  <id>
   720311904
  </id>
  <name>
   Addidas Belts P-8470
  </name>
  <category>
   Belts
  </category>
  <size>
   S
  </size>
  <color>
   Желтый
  </color>
  <material>
   Шерсть
  </material>
  <price>
   609272
  </price>
  <rating>
   2.57
  </rating>
  <reviews>
   925893
  </reviews>
  <new>
   +
  </new>
  <exclusive>
   no
  </exclusive>
  <sporty>
   no
  </sporty>
 </clothing>
 <clothing>
  <id>
   924165075
  </id>
  <name>
   Addidas Skirt K-4079
  </name>
  <category>
   Skirt
  </category>
  <size>
   S
  </size>
  <color>
   Фиолетовый
  </color>
  <material>
   Хлопок
  </material>
  <price>
   651756
  </price>
  <rating>
   3.66
  </rating>
  <reviews>
   124876
  </reviews>
  <new>
   -
  </new>
  <exclusive>
   no
  </exclusive>
 </clothing>
 <clothing>
  <id>
   852498517
  </id>
  <name>
   Nike Hat A-7743
  </name>
  <category>
   Hat
  </category>
  <size>
   XL
  </size>
  <color>
   Желтый
  </color>
  <material>
   Лен
  </material>
  <price>
   860141
  </price>
  <rating>
   2.2
  </rating>
  <reviews>
   245564
  </reviews>
  <exclusive>
   yes
  </exclusive>
 </clothing>
 <clothing>
  <id>
   570430139
  </id>
  <name>
   Reebok T-shirt U-6683
  </name>
  <category>
   T-shirt
  </category>
  <size>
   XXL
  </size>
  <color>
   Желтый
  </color>
  <material>
   Полиэстер
  </material>
  <price>
   975952
  </price>
  <rating>
   4.79
  </rating>
  <reviews>
   582409
  </reviews>
 </clothing>
 <clothing>
  <id>
   843991641
  </id>
  <name>
   New Balance Belts G-7254
  </name>
  <category>
   Belts
  </category>
  <size>
   L
  </size>
  <color>
   Зеленый
  </color>
  <material>
   Полиэстер
  </material>
  <price>
   365402
  </price>
  <rating>
   4.69
  </rating>
  <reviews>
   669516
  </reviews>
 </clothing>
 <clothing>
  <id>
   112072410
  </id>
  <name>
   Asics Socks E-7507
  </name>
  <category>
   Socks
  </category>
  <size>
   XXL
  </size>
  <color>
   Желтый
  </color>
  <material>
   Шелк
  </material>
  <price>
   569772
  </price>
  <rating>
   1.26
  </rating>
  <reviews>
   512355
  </reviews>
  <exclusive>
   no
  </exclusive>
  <sporty>
   no
  </sporty>
 </clothing>
 <clothing>
  <id>
   185325061
  </id>
  <name>
   New Balance Jacket C-8242
  </name>
  <category>
   Jacket
  </category>
  <size>
   XL
  </size>
  <color>
   Фиолетовый
  </color>
  <material>
   Кожа
  </material>
  <price>
   687430
  </price>
  <rating>
   2.52
  </rating>
  <reviews>
   664042
  </reviews>
  <new>
   -
  </new>
  <exclusive>
   yes
  </exclusive>
  <sporty>
   yes
  </sporty>
 </clothing>
 <clothing>
  <id>
   456343335
  </id>
  <name>
   DC Jacket S-3462
  </name>
  <category>
   Jacket
  </category>
  <size>
   XXL
  </size>
  <color>
   Оранжевый
  </color>
  <material>
   Шерсть
  </material>
  <price>
   562342
  </price>
  <rating>
   5.0
  </rating>
  <reviews>
   433685
  </reviews>
  <new>
   +
  </new>
  <exclusive>
   no
  </exclusive>
  <sporty>
   no
  </sporty>
 </clothing>
 <clothing>
  <id>
   488902870
  </id>
  <name>
   Addidas T-shirt H-5857
  </name>
  <category>
   T-shirt
  </category>
  <size>
   S
  </size>
  <color>
   Голубой
  </color>
  <material>
   Вискоза
  </material>
  <price>
   629533
  </price>
  <rating>
   3.0
  </rating>
  <reviews>
   670050
  </reviews>
  <exclusive>
   no
  </exclusive>
  <sporty>
   yes
  </sporty>
 </clothing>
 <clothing>
  <id>
   948562253
  </id>
  <name>
   Asics Shoes J-4750
  </name>
  <category>
   Shoes
  </category>
  <size>
   L
  </size>
  <color>
   Зеленый
  </color>
  <material>
   Кожа
  </material>
  <price>
   464777
  </price>
  <rating>
   4.73
  </rating>
  <reviews>
   784921
  </reviews>
  <exclusive>
   yes
  </exclusive>
 </clothing>
 <clothing>
  <id>
   738293135
  </id>
  <name>
   New Balance Umbrellas C-6658
  </name>
  <category>
   Umbrellas
  </category>
  <size>
   M
  </size>
  <color>
   Желтый
  </color>
  <material>
   Нейлон
  </material>
  <price>
   185473
  </price>
  <rating>
   1.96
  </rating>
  <reviews>
   796211
  </reviews>
  <exclusive>
   yes
  </exclusive>
 </clothing>
 <clothing>
  <id>
   728137722
  </id>
  <name>
   Under Armour Belts W-3269
  </name>
  <category>
   Belts
  </category>
  <size>
   S
  </size>
  <color>
   Красный
  </color>
  <material>
   Лен
  </material>
  <price>
   670323
  </price>
  <rating>
   3.91
  </rating>
  <reviews>
   958067
  </reviews>
  <exclusive>
   no
  </exclusive>
  <sporty>
   yes
  </sporty>
 </clothing>
 <clothing>
  <id>
   185691806
  </id>
  <name>
   Puma Umbrellas W-3355
  </name>
  <category>
   Umbrellas
  </category>
  <size>
   M
  </size>
  <color>
   Желтый
  </color>
  <material>
   Шерсть
  </material>
  <price>
   366236
  </price>
  <rating>
   4.95
  </rating>
  <reviews>
   268521
  </reviews>
  <exclusive>
   no
  </exclusive>
 </clothing>
 <clothing>
  <id>
   156716186
  </id>
  <name>
   Brooks Handbags M-9992
  </name>
  <category>
   Handbags
  </category>
  <size>
   M
  </size>
  <color>
   Зеленый
  </color>
  <material>
   Шелк
  </material>
  <price>
   567310
  </price>
  <rating>
   4.71
  </rating>
  <reviews>
   878999
  </reviews>
  <new>
   +
  </new>
  <sporty>
   no
  </sporty>
 </clothing>
 <clothing>
  <id>
   707038246
  </id>
  <name>
   DC Belts N-9889
  </name>
  <category>
   Belts
  </category>
  <size>
   XL
  </size>
  <color>
   Оранжевый
  </color>
  <material>
   Хлопок
  </material>
  <price>
   465763
  </price>
  <rating>
   3.25
  </rating>
  <reviews>
   17564
  </reviews>
  <exclusive>
   yes
  </exclusive>
 </clothing>
 <clothing>
  <id>
   669413575
  </id>
  <name>
   Converse Shirt O-7887
  </name>
  <category>
   Shirt
  </category>
  <size>
   S
  </size>
  <color>
   Зеленый
  </color>
  <material>
   Шелк
  </material>
  <price>
   866474
  </price>
  <rating>
   4.85
  </rating>
  <reviews>
   512096
  </reviews>
  <new>
   -
  </new>
  <exclusive>
   yes
  </exclusive>
 </clothing>
 <clothing>
  <id>
   409672679
  </id>
  <name>
   Vans Pants Y-7182
  </name>
  <category>
   Pants
  </category>
  <size>
   XXL
  </size>
  <color>
   Фиолетовый
  </color>
  <material>
   Вискоза
  </material>
  <price>
   383604
  </price>
  <rating>
   4.96
  </rating>
  <reviews>
   440416
  </reviews>
  <new>
   +
  </new>
  <exclusive>
   yes
  </exclusive>
 </clothing>
 <clothing>
  <id>
   328142676
  </id>
  <name>
   Vans Umbrellas Z-5087
  </name>
  <category>
   Umbrellas
  </category>
  <size>
   XXL
  </size>
  <color>
   Голубой
  </color>
  <material>
   Хлопок
  </material>
  <price>
   686320
  </price>
  <rating>
   2.14
  </rating>
  <reviews>
   607428
  </reviews>
  <new>
   -
  </new>
  <sporty>
   yes
  </sporty>
 </clothing>
 <clothing>
  <id>
   997026098
  </id>
  <name>
   Puma Pants V-6867
  </name>
  <category>
   Pants
  </category>
  <size>
   XXL
  </size>
  <color>
   Желтый
  </color>
  <material>
   Лен
  </material>
  <price>
   577725
  </price>
  <rating>
   1.23
  </rating>
  <reviews>
   35620
  </reviews>
  <new>
   -
  </new>
  <exclusive>
   no
  </exclusive>
  <sporty>
   no
  </sporty>
 </clothing>
 <clothing>
  <id>
   755416832
  </id>
  <name>
   Puma Handbags Y-4219
  </name>
  <category>
   Handbags
  </category>
  <size>
   L
  </size>
  <color>
   Желтый
  </color>
  <material>
   Кожа
  </material>
  <price>
   253389
  </price>
  <rating>
   4.11
  </rating>
  <reviews>
   399952
  </reviews>
  <new>
   -
  </new>
  <sporty>
   no
  </sporty>
 </clothing>
 <clothing>
  <id>
   716055620
  </id>
  <name>
   Vans Skirt N-7351
  </name>
  <category>
   Skirt
  </category>
  <size>
   L
  </size>
  <color>
   Оранжевый
  </color>
  <material>
   Полиэстер
  </material>
  <price>
   132435
  </price>
  <rating>
   1.12
  </rating>
  <reviews>
   415440
  </reviews>
  <new>
   -
  </new>
  <exclusive>
   yes
  </exclusive>
  <sporty>
   no
  </sporty>
 </clothing>
 <clothing>
  <id>
   384176819
  </id>
  <name>
   New Balance Shoes P-1859
  </name>
  <category>
   Shoes
  </category>
  <size>
   M
  </size>
  <color>
   Фиолетовый
  </color>
  <material>
   Хлопок
  </material>
  <price>
   196309
  </price>
  <rating>
   4.6
  </rating>
  <reviews>
   187887
  </reviews>
  <new>
   -
  </new>
  <exclusive>
   no
  </exclusive>
  <sporty>
   yes
  </sporty>
 </clothing>
 <clothing>
  <id>
   453379818
  </id>
  <name>
   Addidas Shirt L-5213
  </name>
  <category>
   Shirt
  </category>
  <size>
   S
  </size>
  <color>
   Желтый
  </color>
  <material>
   Кожа
  </material>
  <price>
   571831
  </price>
  <rating>
   3.84
  </rating>
  <reviews>
   979947
  </reviews>
  <new>
   +
  </new>
 </clothing>
 <clothing>
  <id>
   293474128
  </id>
  <name>
   Brooks Shoes H-1079
  </name>
  <category>
   Shoes
  </category>
  <size>
   L
  </size>
  <color>
   Синий
  </color>
  <material>
   Шерсть
  </material>
  <price>
   101330
  </price>
  <rating>
   2.59
  </rating>
  <reviews>
   323144
  </reviews>
  <new>
   +
  </new>
  <exclusive>
   no
  </exclusive>
  <sporty>
   yes
  </sporty>
 </clothing>
 <clothing>
  <id>
   165578792
  </id>
  <name>
   DC Blouse T-2069
  </name>
  <category>
   Blouse
  </category>
  <size>
   M
  </size>
  <color>
   Оранжевый
  </color>
  <material>
   Нейлон
  </material>
  <price>
   886030
  </price>
  <rating>
   2.43
  </rating>
  <reviews>
   172335
  </reviews>
  <new>
   -
  </new>
  <exclusive>
   no
  </exclusive>
 </clothing>
 <clothing>
  <id>
   954310267
  </id>
  <name>
   Vans Sweater P-7317
  </name>
  <category>
   Sweater
  </category>
  <size>
   XXL
  </size>
  <color>
   Оранжевый
  </color>
  <material>
   Полиэстер
  </material>
  <price>
   368968
  </price>
  <rating>
   3.31
  </rating>
  <reviews>
   119311
  </reviews>
  <exclusive>
   yes
  </exclusive>
  <sporty>
   no
  </sporty>
 </clothing>
 <clothing>
  <id>
   812660115
  </id>
  <name>
   PleinSport Jeans E-5395
  </name>
  <category>
   Jeans
  </category>
  <size>
   S
  </size>
  <color>
   Зеленый
  </color>
  <material>
   Полиэстер
  </material>
  <price>
   412839
  </price>
  <rating>
   3.74
  </rating>
  <reviews>
   496160
  </reviews>
 </clothing>
 <clothing>
  <id>
   460755083
  </id>
  <name>
   Nike Sweater R-3082
  </name>
  <category>
   Sweater
  </category>
  <size>
   M
  </size>
  <color>
   Фиолетовый
  </color>
  <material>
   Шелк
  </material>
  <price>
   386040
  </price>
  <rating>
   3.68
  </rating>
  <reviews>
   202665
  </reviews>
  <new>
   -
  </new>
  <sporty>
   no
  </sporty>
 </clothing>
 <clothing>
  <id>
   559701714
  </id>
  <name>
   Reebok Skirt R-1862
  </name>
  <category>
   Skirt
  </category>
  <size>
   XL
  </size>
  <color>
   Фиолетовый
  </color>
  <material>
   Шелк
  </material>
  <price>
   998916
  </price>
  <rating>
   4.65
  </rating>
  <reviews>
   716133
  </reviews>
  <new>
   -
  </new>
 </clothing>
 <clothing>
  <id>
   129694838
  </id>
  <name>
   Vans Shoes Y-3464
  </name>
  <category>
   Shoes
  </category>
  <size>
   S
  </size>
  <color>
   Синий
  </color>
  <material>
   Лен
  </material>
  <price>
   524070
  </price>
  <rating>
   2.32
  </rating>
  <reviews>
   172015
  </reviews>
  <sporty>
   no
  </sporty>
 </clothing>
 <clothing>
  <id>
   343438324
  </id>
  <name>
   Ellesse Sweater M-7547
  </name>
  <category>
   Sweater
  </category>
  <size>
   M
  </size>
  <color>
   Оранжевый
  </color>
  <material>
   Полиэстер
  </material>
  <price>
   339853
  </price>
  <rating>
   2.04
  </rating>
  <reviews>
   541219
  </reviews>
  <exclusive>
   yes
  </exclusive>
  <sporty>
   yes
  </sporty>
 </clothing>
 <clothing>
  <id>
   647340525
  </id>
  <name>
   PleinSport Gloves R-3376
  </name>
  <category>
   Gloves
  </category>
  <size>
   S
  </size>
  <color>
   Оранжевый
  </color>
  <material>
   Кожа
  </material>
  <price>
   242727
  </price>
  <rating>
   4.22
  </rating>
  <reviews>
   23014
  </reviews>
  <new>
   -
  </new>
  <exclusive>
   yes
  </exclusive>
 </clothing>
 <clothing>
  <id>
   612234028
  </id>
  <name>
   Puma Pants O-2991
  </name>
  <category>
   Pants
  </category>
  <size>
   S
  </size>
  <color>
   Оранжевый
  </color>
  <material>
   Шерсть
  </material>
  <price>
   969407
  </price>
  <rating>
   4.16
  </rating>
  <reviews>
   901134
  </reviews>
 </clothing>
 <clothing>
  <id>
   670619189
  </id>
  <name>
   Adidas Shoes A-6020
  </name>
  <category>
   Shoes
  </category>
  <size>
   S
  </size>
  <color>
   Фиолетовый
  </color>
  <material>
   Вискоза
  </material>
  <price>
   501559
  </price>
  <rating>
   2.81
  </rating>
  <reviews>
   42486
  </reviews>
  <sporty>
   no
  </sporty>
 </clothing>
 <clothing>
  <id>
   118290457
  </id>
  <name>
   Addidas Shoes T-4324
  </name>
  <category>
   Shoes
  </category>
  <size>
   L
  </size>
  <color>
   Оранжевый
  </color>
  <material>
   Полиэстер
  </material>
  <price>
   622005
  </price>
  <rating>
   1.83
  </rating>
  <reviews>
   89653
  </reviews>
  <exclusive>
   no
  </exclusive>
  <sporty>
   yes
  </sporty>
 </clothing>
 <clothing>
  <id>
   617340462
  </id>
  <name>
   DC Sweater B-4337
  </name>
  <category>
   Sweater
  </category>
  <size>
   S
  </size>
  <color>
   Голубой
  </color>
  <material>
   Вискоза
  </material>
  <price>
   590561
  </price>
  <rating>
   2.89
  </rating>
  <reviews>
   820613
  </reviews>
  <exclusive>
   no
  </exclusive>
  <sporty>
   no
  </sporty>
 </clothing>
 <clothing>
  <id>
   192528404
  </id>
  <name>
   Asics Jacket J-1100
  </name>
  <category>
   Jacket
  </category>
  <size>
   XXL
  </size>
  <color>
   Зеленый
  </color>
  <material>
   Кожа
  </material>
  <price>
   588795
  </price>
  <rating>
   4.73
  </rating>
  <reviews>
   285246
  </reviews>
  <exclusive>
   no
  </exclusive>
  <sporty>
   yes
  </sporty>
 </clothing>
 <clothing>
  <id>
   915245249
  </id>
  <name>
   Converse Blouse S-8122
  </name>
  <category>
   Blouse
  </category>
  <size>
   S
  </size>
  <color>
   Фиолетовый
  </color>
  <material>
   Вискоза
  </material>
  <price>
   663282
  </price>
  <rating>
   4.63
  </rating>
  <reviews>
   835113
  </reviews>
  <new>
   +
  </new>
  <exclusive>
   no
  </exclusive>
 </clothing>
</clothing-items>
